qkernel/__init__.py
qkernel/cli.py
qkernel/daemon.py
qkernel/kernel.py
qkernel/output.py
qkernel/parser.py
qkernel-0.1.1.dist-info/METADATA
qkernel-0.1.1.dist-info/WHEEL
qkernel-0.1.1.dist-info/entry_points.txt
qkernel-0.1.1.dist-info/RECORD
