Metadata-Version: 2.4
Name: qkernel
Version: 0.1.1
Summary: CLI tool for executing Quarto cells through a Jupyter kernel
Requires-Python: >=3.10
Requires-Dist: click>=8.0.0
Requires-Dist: ipykernel>=7.1.0
Requires-Dist: jupyter-client>=8.0.0
Requires-Dist: matplotlib>=3.10.8
Requires-Dist: pyyaml>=6.0.0
Provides-Extra: dev
Requires-Dist: pytest-timeout>=2.0.0; extra == 'dev'
Requires-Dist: pytest>=7.0.0; extra == 'dev'
